koshort/__init__.py
koshort/constants.py
koshort/data.py
koshort/dictionary.py
koshort/threading.py
koshort/utils.py
koshort/stream/__init__.py
koshort/stream/base.py
koshort/stream/dcinside.py
koshort/stream/misc.py
koshort/stream/naver.py
koshort/stream/twitter.py
koshort/stream/dev/__init__.py
koshort/stream/dev/example.py
koshort/stream/dev/setup.py
koshort-0.4.1.2.dist-info/DESCRIPTION.rst
koshort-0.4.1.2.dist-info/METADATA
koshort-0.4.1.2.dist-info/RECORD
koshort-0.4.1.2.dist-info/WHEEL
koshort-0.4.1.2.dist-info/entry_points.txt
koshort-0.4.1.2.dist-info/metadata.json
koshort-0.4.1.2.dist-info/top_level.txt
